lezargus/__init__.py
lezargus/__main__.py
lezargus/__version__.py
lezargus/config.py
lezargus/initialize.py
lezargus/terminate.py
lezargus/cli/__init__.py
lezargus/cli/__main__.py
lezargus/cli/help_.py
lezargus/cli/version.py
lezargus/data/__init__.py
lezargus/data/_files/atmosphere_psg/psg_telluric_radiance.dat
lezargus/data/_files/atmosphere_psg/psg_telluric_transmission.dat
lezargus/data/_files/constants/constants.txt
lezargus/data/_files/irtf_optics/efficiency_irtf_primary_mirror.dat
lezargus/data/_files/irtf_optics/efficiency_irtf_secondary_mirror.dat
lezargus/data/_files/photometric_filters/filter_2MASS_H.dat
lezargus/data/_files/photometric_filters/filter_2MASS_J.dat
lezargus/data/_files/photometric_filters/filter_2MASS_Ks.dat
lezargus/data/_files/photometric_filters/filter_GAIA_BP.dat
lezargus/data/_files/photometric_filters/filter_GAIA_G.dat
lezargus/data/_files/photometric_filters/filter_GAIA_RP.dat
lezargus/data/_files/photometric_filters/filter_GAIA_RVS.dat
lezargus/data/_files/photometric_filters/filter_Johnson_B.dat
lezargus/data/_files/photometric_filters/filter_Johnson_U.dat
lezargus/data/_files/photometric_filters/filter_Johnson_V.dat
lezargus/data/_files/photometric_filters/filter_TYCHO2_BT.dat
lezargus/data/_files/photometric_filters/filter_TYCHO2_VT.dat
lezargus/data/_files/photometric_filters/filter_WISE_1.dat
lezargus/data/_files/photometric_filters/filter_WISE_2.dat
lezargus/data/_files/photometric_filters/filter_WISE_3.dat
lezargus/data/_files/photometric_filters/filter_WISE_4.dat
lezargus/data/_files/spectre_calibrations/midir_spex_lxds_arclamp.dat
lezargus/data/_files/spectre_calibrations/nearir_spex_sxd_arclamp.dat
lezargus/data/_files/spectre_calibrations/visible_hgar_arclamp.dat
lezargus/data/_files/spectre_calibrations/visible_thar_arclamp.dat
lezargus/data/_files/spectre_dispersion/spectre_slice_dispersion.dat
lezargus/data/_files/spectre_dispersion/spectre_slice_pattern.dat
lezargus-0.2.4.dist-info/METADATA
lezargus-0.2.4.dist-info/WHEEL
lezargus-0.2.4.dist-info/entry_points.txt
lezargus-0.2.4.dist-info/licenses/LICENSE.txt
lezargus-0.2.4.dist-info/RECORD
