Metadata-Version: 2.4
Name: lezargus
Version: 0.2.4
Summary: The accompanying data software package to the IRTF SPECTRE Spectrograph.
Project-URL: Homepage, http://irtfweb.ifa.hawaii.edu/~spectre/
Project-URL: Repository, https://github.com/psmd-iberutaru/Lezargus/
Project-URL: Documentation, https://psmd-iberutaru.github.io/Lezargus/
Project-URL: Issues, https://github.com/psmd-iberutaru/Lezargus/issues
Author-email: Sparrow <psmd.iberutaru@gmail.com>
License-Expression: MIT
License-File: LICENSE.txt
Classifier: Development Status :: 2 - Pre-Alpha
Classifier: Programming Language :: Python
Classifier: Programming Language :: Python :: 3.11
Classifier: Programming Language :: Python :: Implementation :: CPython
Classifier: Programming Language :: Python :: Implementation :: PyPy
Requires-Python: >=3.11
Requires-Dist: astropy>=6.1.0
Requires-Dist: colorama==0.4.6
Requires-Dist: matplotlib>=3.9.0
Requires-Dist: numpy>=2.0.0
Requires-Dist: opencv-python-headless>=4.13.0
Requires-Dist: pyside6>=6.8.0
Requires-Dist: pyyaml>=6.0.0
Requires-Dist: scipy>=1.14.1
